{
    "getAll":["select heroID, name, yearOfBirth, gear, costume from superheros"],
    "get":[
        "select heroID, name, yearOfBirth, gear, costume from superheros",
        "where heroID=?"
    ],
    "insert":[
        "insert into superheros (heroID, name, yearOfBirth, gear, costume)",
        "values(?,?,?,?,?)"
    ],
    "update":[
        "update superheros set name=?, yearOfBirth=?, gear=?, costume=?",
        "where heroID=?"
    ],
    "remove":["delete from superheros where heroID=?"],
    "primaryKey":"heroID",
    "resource":"superheros"
}